light_pipe/__init__.py
light_pipe/data.py
light_pipe/parallelizer.py
light_pipe/transformer.py
light_pipe-0.3.1.dist-info/LICENSE
light_pipe-0.3.1.dist-info/METADATA
light_pipe-0.3.1.dist-info/WHEEL
light_pipe-0.3.1.dist-info/top_level.txt
light_pipe-0.3.1.dist-info/RECORD
