Metadata-Version: 2.1
Name: light-pipe
Version: 0.3.1
Home-page: https://github.com/rcorrero/light-pipe
Author: Richard Correro
Author-email: richard@richardcorrero.com
License: BSD 3-Clause
License-File: LICENSE
